nengo_ssp/__init__.py
nengo_ssp/dists.py
nengo_ssp/hrr_algebra.py
nengo_ssp/networks.py
nengo_ssp/plotting.py
nengo_ssp/spatial_semantic_pointer.py
nengo_ssp/utils.py
nengo_ssp/vector_generation.py
nengo_ssp-0.1.1.dist-info/AUTHORS.rst
nengo_ssp-0.1.1.dist-info/LICENSE
nengo_ssp-0.1.1.dist-info/METADATA
nengo_ssp-0.1.1.dist-info/WHEEL
nengo_ssp-0.1.1.dist-info/entry_points.txt
nengo_ssp-0.1.1.dist-info/top_level.txt
nengo_ssp-0.1.1.dist-info/RECORD
