Metadata-Version: 2.1
Name: nengo-ssp
Version: 0.1.1
Summary: Spatial Semantic Pointers (SSPs) for nengo and nengo_spa. Grid cell SSPs included.
Home-page: https://github.com/nsdumont/nengo_ssp
Author: Nicole Sandra-Yaffa Dumont
Author-email: nicole.s.dumont@gmail.com
License: MIT license
Keywords: nengo_ssp
Platform: UNKNOWN
Classifier: Development Status :: 2 - Pre-Alpha
Classifier: Intended Audience :: Developers
Classifier: License :: OSI Approved :: MIT License
Classifier: Natural Language :: English
Classifier: Programming Language :: Python :: 3
Classifier: Programming Language :: Python :: 3.5
Classifier: Programming Language :: Python :: 3.6
Classifier: Programming Language :: Python :: 3.7
Classifier: Programming Language :: Python :: 3.8
Requires-Python: >=3.5
Requires-Dist: nengo
Requires-Dist: nengo-spa (==1.0.1)
Requires-Dist: numpy (==1.18.5)
